markdown_rundoc/__init__.py
markdown_rundoc/rundoc_code.py
markdown_rundoc-0.3.0.dist-info/DESCRIPTION.rst
markdown_rundoc-0.3.0.dist-info/METADATA
markdown_rundoc-0.3.0.dist-info/RECORD
markdown_rundoc-0.3.0.dist-info/WHEEL
markdown_rundoc-0.3.0.dist-info/metadata.json
markdown_rundoc-0.3.0.dist-info/top_level.txt
